oztools/__init__.py
oztools/_modidx.py
oztools/core.py
oztools/format.py
oztools/gh.py
oztools/kgl.py
oztools/nbd.py
oztools/data/favicon.png
oztools-0.0.3.dist-info/licenses/LICENSE
oztools-0.0.3.dist-info/METADATA
oztools-0.0.3.dist-info/WHEEL
oztools-0.0.3.dist-info/entry_points.txt
oztools-0.0.3.dist-info/top_level.txt
oztools-0.0.3.dist-info/RECORD
